tyr/__init__.py
tyr/py.typed
tyr-0.0.1.dist-info/WHEEL
tyr-0.0.1.dist-info/METADATA
tyr-0.0.1.dist-info/RECORD
